pyattck_data/__init__.py
pyattck_data/actor.py
pyattck_data/attack.py
pyattck_data/base.py
pyattck_data/campaign.py
pyattck_data/control.py
pyattck_data/datacomponent.py
pyattck_data/datasource.py
pyattck_data/definition.py
pyattck_data/generated.py
pyattck_data/identity.py
pyattck_data/malware.py
pyattck_data/matrix.py
pyattck_data/mitigation.py
pyattck_data/nist.py
pyattck_data/py.typed
pyattck_data/relationship.py
pyattck_data/tactic.py
pyattck_data/technique.py
pyattck_data/tool.py
pyattck_data/types.py
pyattck_data-2.6.2.dist-info/LICENSE.rst
pyattck_data-2.6.2.dist-info/METADATA
pyattck_data-2.6.2.dist-info/WHEEL
pyattck_data-2.6.2.dist-info/LICENSE
pyattck_data-2.6.2.dist-info/RECORD
