Metadata-Version: 2.1
Name: pyattck-data
Version: 2.6.2
Summary: Pyattck Data
Home-page: https://github.com/swimlane/pyattck-data
License: MIT
Author: Swimlane
Author-email: info@swimlane.com
Requires-Python: >=3.7,<4.0
Classifier: Development Status :: 3 - Alpha
Classifier: License :: OSI Approved :: MIT License
Classifier: Programming Language :: Python :: 3
Classifier: Programming Language :: Python :: 3.7
Classifier: Programming Language :: Python :: 3.8
Classifier: Programming Language :: Python :: 3.9
Classifier: Programming Language :: Python :: 3.10
Classifier: Programming Language :: Python :: 3.11
Requires-Dist: PyYAML (>=6.0,<7.0)
Requires-Dist: attrs (>=21.4.0,<22.0.0)
Requires-Dist: importlib-metadata (<3.4)
Requires-Dist: openpyxl (>=3.0.10,<4.0.0)
Requires-Dist: pydantic (>=1.9.1,<2.0.0)
Requires-Dist: requests (>=2.28.0,<3.0.0)
Project-URL: Changelog, https://github.com/swimlane/pyattck-data/releases
Project-URL: Repository, https://github.com/swimlane/pyattck-data
